tblg/__init__.py
tblg/__main__.py
tblg/barcoding.py
tblg/levels.py
tblg/utils.py
tblg/vcf.py
tblg/data/levels.tsv
tblg-0.1.5.dist-info/LICENSE
tblg-0.1.5.dist-info/METADATA
tblg-0.1.5.dist-info/WHEEL
tblg-0.1.5.dist-info/entry_points.txt
tblg-0.1.5.dist-info/top_level.txt
tblg-0.1.5.dist-info/RECORD
