Metadata-Version: 2.1
Name: tblg
Version: 0.1.5
Summary: A command-line tool to genotype Mycobacterium tuberculosis lineage from a VCF file
Home-page: https://github.com/dbespiatykh/tblg
Author: Dmitry Bespiatykh
Author-email: d.bespiatykh@gmail.com
License: MIT
Classifier: Development Status :: 4 - Beta
Classifier: Environment :: Console
Classifier: Intended Audience :: Science/Research
Classifier: License :: OSI Approved :: MIT License
Classifier: Operating System :: POSIX
Classifier: Programming Language :: Python :: 3.10
Classifier: Programming Language :: Python :: 3.11
Classifier: Topic :: Scientific/Engineering :: Bio-Informatics
Requires-Python: >=3.10
License-File: LICENSE
Requires-Dist: click (>=8.0.4)
Requires-Dist: numpy (>=1.23.5)
Requires-Dist: pandas (>=1.5.0)
Requires-Dist: tabulate (>=0.9.0)
Requires-Dist: tqdm (>=4.64.1)
Requires-Dist: rich (>=13.3.1)
Requires-Dist: rich-click (>=1.6.1)
Requires-Dist: datetime (>=5.1)
